{
  "litholog": "Litholog",
  "search": "Search",
  "cancel": "Cancel",
  "confirm": "Confirm",
  "delete": "Delete",
  "auth": {
    "sign-up": "Sign up",
    "email": "E-mail",
    "password": "Password",
    "old-password": "Old password",
    "new-password": "New password",
    "has-account": "Do you have an account?",
    "sign-in": {
      "forgot-password": "Forgot password?",
      "question-for-reg": "You don't have an account?"
    }
  },
  "main": {
    "title": "Best lithology service ever",
    "description": "Fishtext is used by designers, planners and frontenders when they need to quickly populate mockups or prototypes with content.",
    "play-img-label": "Play image"
  },
  "footer": {
    "heading": "Let's go over the details",
    "privacy": "© Drone. All Rights Reserved 2023.",
    "check-socials": "Check our social media",
    "terms-of-use": "Terms of Use",
    "privacy-policy": "Privacy Policy"
  },
  "icons": {
    "notification": "notification",
    "sticker": "sticker",
    "line": "line",
    "instagram": "instagram",
    "youtube": "youtube",
    "facebook": "facebook"
  },
  "navigation": {
    "create": "Create report",
    "home": "Home",
    "folders": "Folders",
    "settings": "Settings",
    "main": "Main",
    "news": "News",
    "support": "Support",
    "sign-in": "Sign in",
    "registration": "Registration",
    "back": "Back",
    "change-password": "Change password",
    "reset-password": "Reset password",
    "email-confirm": "E-mail confirmation",
    "reset-confirm": "Reset confirmation",
    "notifications": {
      "main": "Notifications",
      "mark-all-read": "Mark all as read"
    },
    "all-projects": {
      "main": "All projects",
      "archived": "Archived",
      "favourites": "Favourites",
      "create": "Create project"
    },
    "subscription": {
      "main": "Subscription",
      "purchase": "Subscription purchase"
    },
    "reports": {
      "main": "Reports",
      "all": "All reports",
      "create": "Create report"
    },
    "cabinet": {
      "company": "Company profile",
      "members": "Members",
      "change-email": "Change e-mail",
      "change-password": "Change password",
      "subscribtion": "Subscription"
    }
  },
  "email-sent": "We have sent you an e-mail. Follow the link in the e-mail.",
  "back-to-sign-in": "Back to sign in",
  "email-confirm-page-heading": "Confirm the change at the e-mail",
  "reset-page-heading": "We reset the password",
  "back-to-settings": "Back to settings",
  "you-bought-the": "You bought the ",
  "subscription-expiration-date": "Subscription expiration date: ",
  "tariff": "Tariff",
  "notifications": {
    "title": "{count, plural, =1 {# notification} other {# notifications}}."
  },
  "not-found": {
    "404": "404",
    "heading": "Page not found",
    "back": "Return to home page"
  },
  "table": {
    "fields": {
      "name": "Name",
      "point": "Point",
      "grain": "Grain",
      "area": "Area",
      "orientation": "Orientation",
      "created_at": "Date created"
    },
    "filter-fields": {
      "a-z": "A-Z",
      "creation-date": "Creation date",
      "change-date": "Date of change",
      "comment-date": "Comment date"
    },
    "add-to-favourites": "Add to favourites",
    "add-to-archive": "Add to archive",
    "reports": "{count, plural, =1 {# report} other {# reports}}",
    "created": "Created",
    "project-delete": "Are you sure you want to delete the {project} project?",
    "project-delete-description": "The project can't be taken back.",
    "folder-delete-description": "The folder can't be taken back.",
    "folder-delete": "Are you sure you want to delete the {folder} folder?",
    "report-delete": "Are you sure you want to delete the {report} report?",
    "report-delete-description": "The report can't be taken back."
  },
  "support": {
    "name": "Name",
    "description": "Description",
    "send": "Send"
  },
  "subscription": {
    "title": "Subscription",
    "offers": {
      "free-projects": "Join now to get 50 projects for free",
      "money-back": "15-day money-back guarantee"
    },
    "buy": "Buy"
  }
}
